pyarrow/__init__.py
pyarrow/__version__.py
pyarrow/arrow_utils.py
pyarrow/connect.py
pyarrow/constants.py
pyarrow/exceptions.py
pyarrow/sockets.py
pyarrow_client-1.1.8.dist-info/licenses/LICENSE
pyarrow_client-1.1.8.dist-info/METADATA
pyarrow_client-1.1.8.dist-info/WHEEL
pyarrow_client-1.1.8.dist-info/top_level.txt
pyarrow_client-1.1.8.dist-info/RECORD
