Metadata-Version: 2.4
Name: pyarrow-client
Version: 1.1.8
Summary: Python SDK for Arrow Trading API
Author-email: Abhishek Jain <abhishek.jain@irage.in>, Shubham Jain <shubham.j@irage.in>, Parth Bhandari <parth.b@irage.in>
License: MIT
Requires-Python: >=3.8
License-File: LICENSE
Requires-Dist: requests>=2.25.0
Requires-Dist: websocket-client>=1.0.0
Requires-Dist: pyotp>=2.6.0
Requires-Dist: python-dateutil>=2.8.0
Requires-Dist: urllib3>=1.26.0
Dynamic: license-file
